andi_pip/__init__.py
andi_pip/_nbdev.py
andi_pip/datasets_phenom.py
andi_pip/datasets_theory.py
andi_pip/models_phenom.py
andi_pip/models_theory.py
andi_pip/utils_metrics.py
andi_pip/utils_trajectories.py
andi_pip-0.0.1.dist-info/METADATA
andi_pip-0.0.1.dist-info/WHEEL
andi_pip-0.0.1.dist-info/entry_points.txt
andi_pip-0.0.1.dist-info/top_level.txt
andi_pip-0.0.1.dist-info/RECORD
