Metadata-Version: 2.1
Name: andi-pip
Version: 0.0.1
Summary: andi_pip
Home-page: https://github.com/gorkamunoz/andi_pip/tree/master/
Author: Gorka Muñoz-Gil
Author-email: munoz.gil.gorka@gmail.com
License: Apache Software License 2.0
Keywords: andi-challenge
Platform: UNKNOWN
Classifier: Development Status :: 3 - Alpha
Classifier: Intended Audience :: Developers
Classifier: Natural Language :: English
Classifier: Programming Language :: Python :: 3.6
Classifier: Programming Language :: Python :: 3.7
Classifier: Programming Language :: Python :: 3.8
Classifier: License :: OSI Approved :: Apache Software License
Requires-Python: >=3.6
Requires-Dist: pip
Requires-Dist: packaging
Requires-Dist: numpy
Provides-Extra: dev
